embeds/__init__.py
embeds/embeds.py
embeds-0.0.3.dist-info/METADATA
embeds-0.0.3.dist-info/WHEEL
embeds-0.0.3.dist-info/top_level.txt
embeds-0.0.3.dist-info/RECORD
