Metadata-Version: 2.1
Name: embeds
Version: 0.0.3
Summary: Send embedded discord messages through your bot!
Author: Lithium
